cocotbext/wishbone/__init__.py
cocotbext/wishbone/driver.py
cocotbext/wishbone/monitor.py
cocotbext/wishbone/version.py
cocotbext_wishbone-0.2.2.dist-info/METADATA
cocotbext_wishbone-0.2.2.dist-info/WHEEL
cocotbext_wishbone-0.2.2.dist-info/top_level.txt
cocotbext_wishbone-0.2.2.dist-info/RECORD
